{
    "2002":
      {
         "Alabama":{
            "Value":8.50,
            "ConfidenceIntervalLow":7.50,
            "ConfidenceIntervalHigh":9.60,
            "StandardError":0.52
         },
         "Alaska":{
            "Value":3.50,
            "ConfidenceIntervalLow":2.80,
            "ConfidenceIntervalHigh":4.40,
            "StandardError":0.41
         },
         "Arizona":{
            "Value":6.40,
            "ConfidenceIntervalLow":5.40,
            "ConfidenceIntervalHigh":7.60,
            "StandardError":0.57
         },
         "Arkansas":{
            "Value":7.90,
            "ConfidenceIntervalLow":7.00,
            "ConfidenceIntervalHigh":8.80,
            "StandardError":0.46
         },
         "California":{
            "Value":7.40,
            "ConfidenceIntervalLow":6.40,
            "ConfidenceIntervalHigh":8.60,
            "StandardError":0.55
         },
         "Colorado":{
            "Value":4.40,
            "ConfidenceIntervalLow":3.80,
            "ConfidenceIntervalHigh":5.20,
            "StandardError":0.36
         },
         "Connecticut":{
            "Value":5.90,
            "ConfidenceIntervalLow":5.20,
            "ConfidenceIntervalHigh":6.70,
            "StandardError":0.38
         },
         "Delaware":{
            "Value":7.10,
            "ConfidenceIntervalLow":6.20,
            "ConfidenceIntervalHigh":8.30,
            "StandardError":0.54
         },
         "District of Columbia":{
            "Value":7.60,
            "ConfidenceIntervalLow":6.30,
            "ConfidenceIntervalHigh":9.20,
            "StandardError":0.74
         },
         "Florida":{
            "Value":7.60,
            "ConfidenceIntervalLow":6.80,
            "ConfidenceIntervalHigh":8.40,
            "StandardError":0.41
         },
         "Georgia":{
            "Value":7.10,
            "ConfidenceIntervalLow":6.30,
            "ConfidenceIntervalHigh":7.90,
            "StandardError":0.42
         },
         "Hawaii":{
            "Value":5.80,
            "ConfidenceIntervalLow":5.10,
            "ConfidenceIntervalHigh":6.60,
            "StandardError":0.39
         },
         "Idaho":{
            "Value":6.10,
            "ConfidenceIntervalLow":5.40,
            "ConfidenceIntervalHigh":6.90,
            "StandardError":0.39
         },
         "Illinois":{
            "Value":6.80,
            "ConfidenceIntervalLow":6.10,
            "ConfidenceIntervalHigh":7.70,
            "StandardError":0.40
         },
         "Indiana":{
            "Value":7.40,
            "ConfidenceIntervalLow":6.70,
            "ConfidenceIntervalHigh":8.20,
            "StandardError":0.38
         },
         "Iowa":{
            "Value":6.50,
            "ConfidenceIntervalLow":5.70,
            "ConfidenceIntervalHigh":7.50,
            "StandardError":0.46
         },
         "Kansas":{
            "Value":6.40,
            "ConfidenceIntervalLow":5.70,
            "ConfidenceIntervalHigh":7.20,
            "StandardError":0.37
         },
         "Kentucky":{
            "Value":7.00,
            "ConfidenceIntervalLow":6.20,
            "ConfidenceIntervalHigh":7.90,
            "StandardError":0.41
         },
         "Louisiana":{
            "Value":7.10,
            "ConfidenceIntervalLow":6.20,
            "ConfidenceIntervalHigh":8.00,
            "StandardError":0.44
         },
         "Maine":{
            "Value":7.30,
            "ConfidenceIntervalLow":6.20,
            "ConfidenceIntervalHigh":8.50,
            "StandardError":0.58
         },
         "Maryland":{
            "Value":6.90,
            "ConfidenceIntervalLow":6.00,
            "ConfidenceIntervalHigh":8.00,
            "StandardError":0.51
         },
         "Massachusetts":{
            "Value":5.80,
            "ConfidenceIntervalLow":5.20,
            "ConfidenceIntervalHigh":6.50,
            "StandardError":0.33
         },
         "Michigan":{
            "Value":7.90,
            "ConfidenceIntervalLow":7.10,
            "ConfidenceIntervalHigh":8.80,
            "StandardError":0.41
         },
         "Minnesota":{
            "Value":4.90,
            "ConfidenceIntervalLow":4.30,
            "ConfidenceIntervalHigh":5.60,
            "StandardError":0.34
         },
         "Mississippi":{
            "Value":8.60,
            "ConfidenceIntervalLow":7.70,
            "ConfidenceIntervalHigh":9.50,
            "StandardError":0.47
         },
         "Missouri":{
            "Value":7.30,
            "ConfidenceIntervalLow":6.40,
            "ConfidenceIntervalHigh":8.30,
            "StandardError":0.48
         },
         "Montana":{
            "Value":5.50,
            "ConfidenceIntervalLow":4.60,
            "ConfidenceIntervalHigh":6.50,
            "StandardError":0.48
         },
         "Nebraska":{
            "Value":5.80,
            "ConfidenceIntervalLow":5.10,
            "ConfidenceIntervalHigh":6.70,
            "StandardError":0.40
         },
         "Nevada":{
            "Value":6.20,
            "ConfidenceIntervalLow":5.10,
            "ConfidenceIntervalHigh":7.60,
            "StandardError":0.62
         },
         "New Hampshire":{
            "Value":6.20,
            "ConfidenceIntervalLow":5.50,
            "ConfidenceIntervalHigh":7.00,
            "StandardError":0.37
         },
         "New Jersey":{
            "Value":6.10,
            "ConfidenceIntervalLow":5.10,
            "ConfidenceIntervalHigh":7.20,
            "StandardError":0.53
         },
         "New Mexico":{
            "Value":6.20,
            "ConfidenceIntervalLow":5.50,
            "ConfidenceIntervalHigh":7.00,
            "StandardError":0.40
         },
         "New York":{
            "Value":7.20,
            "ConfidenceIntervalLow":6.30,
            "ConfidenceIntervalHigh":8.20,
            "StandardError":0.49
         },
         "North Carolina":{
            "Value":7.20,
            "ConfidenceIntervalLow":6.40,
            "ConfidenceIntervalHigh":8.10,
            "StandardError":0.44
         },
         "North Dakota":{
            "Value":6.10,
            "ConfidenceIntervalLow":5.30,
            "ConfidenceIntervalHigh":7.10,
            "StandardError":0.46
         },
         "Ohio":{
            "Value":7.70,
            "ConfidenceIntervalLow":6.80,
            "ConfidenceIntervalHigh":8.70,
            "StandardError":0.49
         },
         "Oklahoma":{
            "Value":6.70,
            "ConfidenceIntervalLow":6.20,
            "ConfidenceIntervalHigh":7.40,
            "StandardError":0.31
         },
         "Oregon":{
            "Value":6.20,
            "ConfidenceIntervalLow":5.30,
            "ConfidenceIntervalHigh":7.30,
            "StandardError":0.51
         },
         "Pennsylvania":{
            "Value":8.10,
            "ConfidenceIntervalLow":7.50,
            "ConfidenceIntervalHigh":8.70,
            "StandardError":0.31
         },
         "Rhode Island":{
            "Value":5.60,
            "ConfidenceIntervalLow":4.90,
            "ConfidenceIntervalHigh":6.50,
            "StandardError":0.40
         },
         "South Carolina":{
            "Value":8.40,
            "ConfidenceIntervalLow":7.40,
            "ConfidenceIntervalHigh":9.50,
            "StandardError":0.53
         },
         "South Dakota":{
            "Value":6.30,
            "ConfidenceIntervalLow":5.50,
            "ConfidenceIntervalHigh":7.10,
            "StandardError":0.41
         },
         "Tennessee":{
            "Value":8.50,
            "ConfidenceIntervalLow":7.40,
            "ConfidenceIntervalHigh":9.60,
            "StandardError":0.56
         },
         "Texas":{
            "Value":7.00,
            "ConfidenceIntervalLow":6.30,
            "ConfidenceIntervalHigh":7.70,
            "StandardError":0.36
         },
         "Utah":{
            "Value":4.40,
            "ConfidenceIntervalLow":3.60,
            "ConfidenceIntervalHigh":5.30,
            "StandardError":0.43
         },
         "Vermont":{
            "Value":5.90,
            "ConfidenceIntervalLow":5.20,
            "ConfidenceIntervalHigh":6.80,
            "StandardError":0.40
         },
         "Virginia":{
            "Value":6.20,
            "ConfidenceIntervalLow":5.40,
            "ConfidenceIntervalHigh":7.20,
            "StandardError":0.45
         },
         "Washington":{
            "Value":5.80,
            "ConfidenceIntervalLow":5.00,
            "ConfidenceIntervalHigh":6.60,
            "StandardError":0.41
         },
         "West Virginia":{
            "Value":10.20,
            "ConfidenceIntervalLow":9.10,
            "ConfidenceIntervalHigh":11.30,
            "StandardError":0.57
         },
         "Wisconsin":{
            "Value":5.10,
            "ConfidenceIntervalLow":4.40,
            "ConfidenceIntervalHigh":5.90,
            "StandardError":0.36
         },
         "Wyoming":{
            "Value":5.60,
            "ConfidenceIntervalLow":4.90,
            "ConfidenceIntervalHigh":6.50,
            "StandardError":0.41
         }
      },

    "2003":
      {
         "Alabama":{
            "Value":8.70,
            "ConfidenceIntervalLow":7.70,
            "ConfidenceIntervalHigh":9.80,
            "StandardError":0.54
         },
         "Alaska":{
            "Value":5.00,
            "ConfidenceIntervalLow":3.90,
            "ConfidenceIntervalHigh":6.40,
            "StandardError":0.63
         },
         "Arizona":{
            "Value":6.30,
            "ConfidenceIntervalLow":5.30,
            "ConfidenceIntervalHigh":7.50,
            "StandardError":0.57
         },
         "Arkansas":{
            "Value":7.40,
            "ConfidenceIntervalLow":6.60,
            "ConfidenceIntervalHigh":8.30,
            "StandardError":0.44
         },
         "California":{
            "Value":7.20,
            "ConfidenceIntervalLow":6.30,
            "ConfidenceIntervalHigh":8.20,
            "StandardError":0.48
         },
         "Colorado":{
            "Value":4.70,
            "ConfidenceIntervalLow":4.10,
            "ConfidenceIntervalHigh":5.50,
            "StandardError":0.36
         },
         "Connecticut":{
            "Value":5.90,
            "ConfidenceIntervalLow":5.30,
            "ConfidenceIntervalHigh":6.70,
            "StandardError":0.36
         },
         "Delaware":{
            "Value":7.70,
            "ConfidenceIntervalLow":6.70,
            "ConfidenceIntervalHigh":8.70,
            "StandardError":0.52
         },
         "District of Columbia":{
            "Value":8.20,
            "ConfidenceIntervalLow":6.80,
            "ConfidenceIntervalHigh":9.90,
            "StandardError":0.76
         },
         "Florida":{
            "Value":8.50,
            "ConfidenceIntervalLow":7.40,
            "ConfidenceIntervalHigh":9.60,
            "StandardError":0.56
         },
         "Georgia":{
            "Value":7.80,
            "ConfidenceIntervalLow":7.00,
            "ConfidenceIntervalHigh":8.60,
            "StandardError":0.40
         },
         "Hawaii":{
            "Value":7.60,
            "ConfidenceIntervalLow":6.60,
            "ConfidenceIntervalHigh":8.70,
            "StandardError":0.53
         },
         "Idaho":{
            "Value":6.30,
            "ConfidenceIntervalLow":5.50,
            "ConfidenceIntervalHigh":7.10,
            "StandardError":0.41
         },
         "Illinois":{
            "Value":7.30,
            "ConfidenceIntervalLow":6.50,
            "ConfidenceIntervalHigh":8.20,
            "StandardError":0.41
         },
         "Indiana":{
            "Value":7.80,
            "ConfidenceIntervalLow":7.00,
            "ConfidenceIntervalHigh":8.60,
            "StandardError":0.39
         },
         "Iowa":{
            "Value":6.70,
            "ConfidenceIntervalLow":6.00,
            "ConfidenceIntervalHigh":7.50,
            "StandardError":0.39
         },
         "Kansas":{
            "Value":6.00,
            "ConfidenceIntervalLow":5.30,
            "ConfidenceIntervalHigh":6.80,
            "StandardError":0.37
         },
         "Kentucky":{
            "Value":8.50,
            "ConfidenceIntervalLow":7.70,
            "ConfidenceIntervalHigh":9.50,
            "StandardError":0.44
         },
         "Louisiana":{
            "Value":8.50,
            "ConfidenceIntervalLow":7.70,
            "ConfidenceIntervalHigh":9.40,
            "StandardError":0.44
         },
         "Maine":{
            "Value":7.40,
            "ConfidenceIntervalLow":6.40,
            "ConfidenceIntervalHigh":8.60,
            "StandardError":0.57
         },
         "Maryland":{
            "Value":7.00,
            "ConfidenceIntervalLow":6.10,
            "ConfidenceIntervalHigh":8.00,
            "StandardError":0.47
         },
         "Massachusetts":{
            "Value":6.20,
            "ConfidenceIntervalLow":5.50,
            "ConfidenceIntervalHigh":6.80,
            "StandardError":0.34
         },
         "Michigan":{
            "Value":7.90,
            "ConfidenceIntervalLow":7.00,
            "ConfidenceIntervalHigh":8.90,
            "StandardError":0.48
         },
         "Minnesota":{
            "Value":5.50,
            "ConfidenceIntervalLow":4.80,
            "ConfidenceIntervalHigh":6.30,
            "StandardError":0.37
         },
         "Mississippi":{
            "Value":11.00,
            "ConfidenceIntervalLow":10.00,
            "ConfidenceIntervalHigh":12.10,
            "StandardError":0.52
         },
         "Missouri":{
            "Value":6.90,
            "ConfidenceIntervalLow":6.10,
            "ConfidenceIntervalHigh":7.90,
            "StandardError":0.47
         },
         "Montana":{
            "Value":5.50,
            "ConfidenceIntervalLow":4.70,
            "ConfidenceIntervalHigh":6.40,
            "StandardError":0.43
         },
         "Nebraska":{
            "Value":6.40,
            "ConfidenceIntervalLow":5.70,
            "ConfidenceIntervalHigh":7.10,
            "StandardError":0.36
         },
         "Nevada":{
            "Value":6.30,
            "ConfidenceIntervalLow":5.20,
            "ConfidenceIntervalHigh":7.60,
            "StandardError":0.63
         },
         "New Hampshire":{
            "Value":5.60,
            "ConfidenceIntervalLow":5.00,
            "ConfidenceIntervalHigh":6.30,
            "StandardError":0.33
         },
         "New Jersey":{
            "Value":7.10,
            "ConfidenceIntervalLow":6.60,
            "ConfidenceIntervalHigh":7.70,
            "StandardError":0.28
         },
         "New Mexico":{
            "Value":5.70,
            "ConfidenceIntervalLow":5.10,
            "ConfidenceIntervalHigh":6.40,
            "StandardError":0.34
         },
         "New York":{
            "Value":7.40,
            "ConfidenceIntervalLow":6.70,
            "ConfidenceIntervalHigh":8.30,
            "StandardError":0.42
         },
         "North Carolina":{
            "Value":8.10,
            "ConfidenceIntervalLow":7.40,
            "ConfidenceIntervalHigh":8.90,
            "StandardError":0.38
         },
         "North Dakota":{
            "Value":6.20,
            "ConfidenceIntervalLow":5.40,
            "ConfidenceIntervalHigh":7.10,
            "StandardError":0.44
         },
         "Ohio":{
            "Value":8.90,
            "ConfidenceIntervalLow":7.80,
            "ConfidenceIntervalHigh":10.10,
            "StandardError":0.58
         },
         "Oklahoma":{
            "Value":7.20,
            "ConfidenceIntervalLow":6.70,
            "ConfidenceIntervalHigh":7.80,
            "StandardError":0.30
         },
         "Oregon":{
            "Value":6.30,
            "ConfidenceIntervalLow":5.50,
            "ConfidenceIntervalHigh":7.10,
            "StandardError":0.41
         },
         "Pennsylvania":{
            "Value":8.00,
            "ConfidenceIntervalLow":7.10,
            "ConfidenceIntervalHigh":9.10,
            "StandardError":0.50
         },
         "Rhode Island":{
            "Value":6.80,
            "ConfidenceIntervalLow":6.00,
            "ConfidenceIntervalHigh":7.80,
            "StandardError":0.47
         },
         "South Carolina":{
            "Value":9.30,
            "ConfidenceIntervalLow":8.50,
            "ConfidenceIntervalHigh":10.20,
            "StandardError":0.44
         },
         "South Dakota":{
            "Value":7.10,
            "ConfidenceIntervalLow":6.40,
            "ConfidenceIntervalHigh":7.80,
            "StandardError":0.37
         },
         "Tennessee":{
            "Value":9.40,
            "ConfidenceIntervalLow":8.20,
            "ConfidenceIntervalHigh":10.80,
            "StandardError":0.66
         },
         "Texas":{
            "Value":8.10,
            "ConfidenceIntervalLow":7.30,
            "ConfidenceIntervalHigh":8.90,
            "StandardError":0.39
         },
         "Utah":{
            "Value":5.50,
            "ConfidenceIntervalLow":4.70,
            "ConfidenceIntervalHigh":6.40,
            "StandardError":0.44
         },
         "Vermont":{
            "Value":5.80,
            "ConfidenceIntervalLow":5.10,
            "ConfidenceIntervalHigh":6.60,
            "StandardError":0.39
         },
         "Virginia":{
            "Value":7.20,
            "ConfidenceIntervalLow":6.40,
            "ConfidenceIntervalHigh":8.10,
            "StandardError":0.43
         },
         "Washington":{
            "Value":6.60,
            "ConfidenceIntervalLow":6.20,
            "ConfidenceIntervalHigh":7.10,
            "StandardError":0.22
         },
         "West Virginia":{
            "Value":9.80,
            "ConfidenceIntervalLow":8.80,
            "ConfidenceIntervalHigh":10.90,
            "StandardError":0.54
         },
         "Wisconsin":{
            "Value":6.00,
            "ConfidenceIntervalLow":5.20,
            "ConfidenceIntervalHigh":6.90,
            "StandardError":0.43
         },
         "Wyoming":{
            "Value":5.80,
            "ConfidenceIntervalLow":5.10,
            "ConfidenceIntervalHigh":6.60,
            "StandardError":0.39
         }
      },
    "2004":
      {
         "Alabama":{
            "Value":8.10,
            "ConfidenceIntervalLow":7.20,
            "ConfidenceIntervalHigh":9.10,
            "StandardError":0.47
         },
         "Alaska":{
            "Value":4.20,
            "ConfidenceIntervalLow":3.20,
            "ConfidenceIntervalHigh":5.30,
            "StandardError":0.53
         },
         "Arizona":{
            "Value":6.60,
            "ConfidenceIntervalLow":5.60,
            "ConfidenceIntervalHigh":7.90,
            "StandardError":0.57
         },
         "Arkansas":{
            "Value":7.10,
            "ConfidenceIntervalLow":6.30,
            "ConfidenceIntervalHigh":7.90,
            "StandardError":0.41
         },
         "California":{
            "Value":7.10,
            "ConfidenceIntervalLow":6.20,
            "ConfidenceIntervalHigh":8.10,
            "StandardError":0.48
         },
         "Colorado":{
            "Value":4.30,
            "ConfidenceIntervalLow":3.70,
            "ConfidenceIntervalHigh":5.00,
            "StandardError":0.32
         },
         "Connecticut":{
            "Value":6.00,
            "ConfidenceIntervalLow":5.40,
            "ConfidenceIntervalHigh":6.70,
            "StandardError":0.34
         },
         "Delaware":{
            "Value":7.00,
            "ConfidenceIntervalLow":6.10,
            "ConfidenceIntervalHigh":8.00,
            "StandardError":0.50
         },
         "District of Columbia":{
            "Value":8.30,
            "ConfidenceIntervalLow":7.10,
            "ConfidenceIntervalHigh":9.60,
            "StandardError":0.62
         },
         "Florida":{
            "Value":7.80,
            "ConfidenceIntervalLow":7.00,
            "ConfidenceIntervalHigh":8.70,
            "StandardError":0.43
         },
         "Georgia":{
            "Value":7.30,
            "ConfidenceIntervalLow":6.50,
            "ConfidenceIntervalHigh":8.20,
            "StandardError":0.44
         },
         "Idaho":{
            "Value":6.10,
            "ConfidenceIntervalLow":5.50,
            "ConfidenceIntervalHigh":6.90,
            "StandardError":0.36
         },
         "Illinois":{
            "Value":6.00,
            "ConfidenceIntervalLow":5.20,
            "ConfidenceIntervalHigh":6.90,
            "StandardError":0.42
         },
         "Indiana":{
            "Value":7.70,
            "ConfidenceIntervalLow":7.10,
            "ConfidenceIntervalHigh":8.50,
            "StandardError":0.36
         },
         "Iowa":{
            "Value":6.40,
            "ConfidenceIntervalLow":5.70,
            "ConfidenceIntervalHigh":7.20,
            "StandardError":0.36
         },
         "Kansas":{
            "Value":6.50,
            "ConfidenceIntervalLow":6.00,
            "ConfidenceIntervalHigh":7.00,
            "StandardError":0.27
         },
         "Kentucky":{
            "Value":7.50,
            "ConfidenceIntervalLow":6.80,
            "ConfidenceIntervalHigh":8.30,
            "StandardError":0.40
         },
         "Louisiana":{
            "Value":8.30,
            "ConfidenceIntervalLow":7.60,
            "ConfidenceIntervalHigh":9.00,
            "StandardError":0.34
         },
         "Maine":{
            "Value":7.50,
            "ConfidenceIntervalLow":6.50,
            "ConfidenceIntervalHigh":8.50,
            "StandardError":0.50
         },
         "Maryland":{
            "Value":7.20,
            "ConfidenceIntervalLow":6.20,
            "ConfidenceIntervalHigh":8.20,
            "StandardError":0.51
         },
         "Massachusetts":{
            "Value":5.60,
            "ConfidenceIntervalLow":5.00,
            "ConfidenceIntervalHigh":6.30,
            "StandardError":0.32
         },
         "Michigan":{
            "Value":7.70,
            "ConfidenceIntervalLow":6.90,
            "ConfidenceIntervalHigh":8.50,
            "StandardError":0.40
         },
         "Minnesota":{
            "Value":5.00,
            "ConfidenceIntervalLow":4.40,
            "ConfidenceIntervalHigh":5.80,
            "StandardError":0.34
         },
         "Mississippi":{
            "Value":9.60,
            "ConfidenceIntervalLow":8.70,
            "ConfidenceIntervalHigh":10.40,
            "StandardError":0.43
         },
         "Missouri":{
            "Value":7.30,
            "ConfidenceIntervalLow":6.50,
            "ConfidenceIntervalHigh":8.10,
            "StandardError":0.42
         },
         "Montana":{
            "Value":6.00,
            "ConfidenceIntervalLow":5.30,
            "ConfidenceIntervalHigh":6.80,
            "StandardError":0.40
         },
         "Nebraska":{
            "Value":6.30,
            "ConfidenceIntervalLow":5.70,
            "ConfidenceIntervalHigh":6.90,
            "StandardError":0.31
         },
         "Nevada":{
            "Value":6.40,
            "ConfidenceIntervalLow":5.30,
            "ConfidenceIntervalHigh":7.70,
            "StandardError":0.61
         },
         "New Hampshire":{
            "Value":6.50,
            "ConfidenceIntervalLow":5.80,
            "ConfidenceIntervalHigh":7.30,
            "StandardError":0.37
         },
         "New Jersey":{
            "Value":6.80,
            "ConfidenceIntervalLow":6.30,
            "ConfidenceIntervalHigh":7.30,
            "StandardError":0.26
         },
         "New Mexico":{
            "Value":6.50,
            "ConfidenceIntervalLow":5.90,
            "ConfidenceIntervalHigh":7.30,
            "StandardError":0.36
         },
         "New York":{
            "Value":7.50,
            "ConfidenceIntervalLow":6.80,
            "ConfidenceIntervalHigh":8.40,
            "StandardError":0.43
         },
         "North Carolina":{
            "Value":8.40,
            "ConfidenceIntervalLow":7.90,
            "ConfidenceIntervalHigh":9.00,
            "StandardError":0.27
         },
         "North Dakota":{
            "Value":5.90,
            "ConfidenceIntervalLow":5.10,
            "ConfidenceIntervalHigh":6.80,
            "StandardError":0.44
         },
         "Ohio":{
            "Value":7.80,
            "ConfidenceIntervalLow":6.70,
            "ConfidenceIntervalHigh":9.10,
            "StandardError":0.60
         },
         "Oklahoma":{
            "Value":8.00,
            "ConfidenceIntervalLow":7.40,
            "ConfidenceIntervalHigh":8.70,
            "StandardError":0.35
         },
         "Oregon":{
            "Value":6.60,
            "ConfidenceIntervalLow":5.90,
            "ConfidenceIntervalHigh":7.40,
            "StandardError":0.37
         },
         "Pennsylvania":{
            "Value":7.80,
            "ConfidenceIntervalLow":7.10,
            "ConfidenceIntervalHigh":8.60,
            "StandardError":0.38
         },
         "Rhode Island":{
            "Value":7.20,
            "ConfidenceIntervalLow":6.30,
            "ConfidenceIntervalHigh":8.10,
            "StandardError":0.46
         },
         "South Carolina":{
            "Value":8.30,
            "ConfidenceIntervalLow":7.60,
            "ConfidenceIntervalHigh":9.00,
            "StandardError":0.35
         },
         "South Dakota":{
            "Value":6.60,
            "ConfidenceIntervalLow":5.90,
            "ConfidenceIntervalHigh":7.30,
            "StandardError":0.35
         },
         "Tennessee":{
            "Value":8.40,
            "ConfidenceIntervalLow":7.40,
            "ConfidenceIntervalHigh":9.50,
            "StandardError":0.53
         },
         "Texas":{
            "Value":7.70,
            "ConfidenceIntervalLow":6.90,
            "ConfidenceIntervalHigh":8.50,
            "StandardError":0.39
         },
         "Utah":{
            "Value":5.10,
            "ConfidenceIntervalLow":4.40,
            "ConfidenceIntervalHigh":5.80,
            "StandardError":0.36
         },
         "Vermont":{
            "Value":5.30,
            "ConfidenceIntervalLow":4.80,
            "ConfidenceIntervalHigh":5.90,
            "StandardError":0.28
         },
         "Virginia":{
            "Value":7.00,
            "ConfidenceIntervalLow":6.30,
            "ConfidenceIntervalHigh":7.90,
            "StandardError":0.41
         },
         "Washington":{
            "Value":6.40,
            "ConfidenceIntervalLow":6.00,
            "ConfidenceIntervalHigh":6.80,
            "StandardError":0.21
         },
         "West Virginia":{
            "Value":10.90,
            "ConfidenceIntervalLow":9.80,
            "ConfidenceIntervalHigh":12.10,
            "StandardError":0.59
         },
         "Wisconsin":{
            "Value":5.70,
            "ConfidenceIntervalLow":5.00,
            "ConfidenceIntervalHigh":6.50,
            "StandardError":0.38
         },
         "Wyoming":{
            "Value":6.00,
            "ConfidenceIntervalLow":5.30,
            "ConfidenceIntervalHigh":6.80,
            "StandardError":0.39
         }
      },
    "2005":
      {
         "Alabama":{
            "Value":9.80,
            "ConfidenceIntervalLow":8.70,
            "ConfidenceIntervalHigh":10.90,
            "StandardError":0.58
         },
         "Alaska":{
            "Value":4.40,
            "ConfidenceIntervalLow":3.50,
            "ConfidenceIntervalHigh":5.50,
            "StandardError":0.51
         },
         "Arizona":{
            "Value":7.50,
            "ConfidenceIntervalLow":6.20,
            "ConfidenceIntervalHigh":8.90,
            "StandardError":0.67
         },
         "Arkansas":{
            "Value":8.10,
            "ConfidenceIntervalLow":7.30,
            "ConfidenceIntervalHigh":8.90,
            "StandardError":0.40
         },
         "California":{
            "Value":7.10,
            "ConfidenceIntervalLow":6.20,
            "ConfidenceIntervalHigh":8.00,
            "StandardError":0.45
         },
         "Colorado":{
            "Value":4.80,
            "ConfidenceIntervalLow":4.20,
            "ConfidenceIntervalHigh":5.40,
            "StandardError":0.29
         },
         "Connecticut":{
            "Value":6.50,
            "ConfidenceIntervalLow":5.80,
            "ConfidenceIntervalHigh":7.30,
            "StandardError":0.39
         },
         "Delaware":{
            "Value":8.60,
            "ConfidenceIntervalLow":7.50,
            "ConfidenceIntervalHigh":9.70,
            "StandardError":0.57
         },
         "District of Columbia":{
            "Value":7.10,
            "ConfidenceIntervalLow":6.20,
            "ConfidenceIntervalHigh":8.10,
            "StandardError":0.50
         },
         "Florida":{
            "Value":8.80,
            "ConfidenceIntervalLow":8.00,
            "ConfidenceIntervalHigh":9.80,
            "StandardError":0.46
         },
         "Georgia":{
            "Value":8.30,
            "ConfidenceIntervalLow":7.50,
            "ConfidenceIntervalHigh":9.30,
            "StandardError":0.48
         },
         "Hawaii":{
            "Value":7.30,
            "ConfidenceIntervalLow":6.50,
            "ConfidenceIntervalHigh":8.30,
            "StandardError":0.45
         },
         "Idaho":{
            "Value":6.80,
            "ConfidenceIntervalLow":6.10,
            "ConfidenceIntervalHigh":7.60,
            "StandardError":0.37
         },
         "Illinois":{
            "Value":7.90,
            "ConfidenceIntervalLow":7.00,
            "ConfidenceIntervalHigh":8.90,
            "StandardError":0.48
         },
         "Indiana":{
            "Value":8.30,
            "ConfidenceIntervalLow":7.60,
            "ConfidenceIntervalHigh":9.20,
            "StandardError":0.40
         },
         "Iowa":{
            "Value":6.80,
            "ConfidenceIntervalLow":6.10,
            "ConfidenceIntervalHigh":7.60,
            "StandardError":0.37
         },
         "Kansas":{
            "Value":6.90,
            "ConfidenceIntervalLow":6.40,
            "ConfidenceIntervalHigh":7.50,
            "StandardError":0.29
         },
         "Kentucky":{
            "Value":8.90,
            "ConfidenceIntervalLow":8.00,
            "ConfidenceIntervalHigh":9.90,
            "StandardError":0.47
         },
         "Louisiana":{
            "Value":9.20,
            "ConfidenceIntervalLow":8.10,
            "ConfidenceIntervalHigh":10.40,
            "StandardError":0.57
         },
         "Maine":{
            "Value":7.50,
            "ConfidenceIntervalLow":6.60,
            "ConfidenceIntervalHigh":8.40,
            "StandardError":0.46
         },
         "Maryland":{
            "Value":7.20,
            "ConfidenceIntervalLow":6.60,
            "ConfidenceIntervalHigh":7.80,
            "StandardError":0.32
         },
         "Massachusetts":{
            "Value":6.40,
            "ConfidenceIntervalLow":5.80,
            "ConfidenceIntervalHigh":7.00,
            "StandardError":0.32
         },
         "Michigan":{
            "Value":8.10,
            "ConfidenceIntervalLow":7.60,
            "ConfidenceIntervalHigh":8.70,
            "StandardError":0.27
         },
         "Minnesota":{
            "Value":5.80,
            "ConfidenceIntervalLow":4.90,
            "ConfidenceIntervalHigh":6.70,
            "StandardError":0.45
         },
         "Mississippi":{
            "Value":9.80,
            "ConfidenceIntervalLow":8.90,
            "ConfidenceIntervalHigh":10.70,
            "StandardError":0.48
         },
         "Missouri":{
            "Value":7.70,
            "ConfidenceIntervalLow":6.90,
            "ConfidenceIntervalHigh":8.70,
            "StandardError":0.46
         },
         "Montana":{
            "Value":5.70,
            "ConfidenceIntervalLow":4.90,
            "ConfidenceIntervalHigh":6.40,
            "StandardError":0.38
         },
         "Nebraska":{
            "Value":7.30,
            "ConfidenceIntervalLow":6.70,
            "ConfidenceIntervalHigh":8.00,
            "StandardError":0.33
         },
         "Nevada":{
            "Value":7.10,
            "ConfidenceIntervalLow":6.00,
            "ConfidenceIntervalHigh":8.40,
            "StandardError":0.62
         },
         "New Hampshire":{
            "Value":6.50,
            "ConfidenceIntervalLow":5.80,
            "ConfidenceIntervalHigh":7.20,
            "StandardError":0.34
         },
         "New Jersey":{
            "Value":7.70,
            "ConfidenceIntervalLow":7.10,
            "ConfidenceIntervalHigh":8.30,
            "StandardError":0.29
         },
         "New Mexico":{
            "Value":7.30,
            "ConfidenceIntervalLow":6.50,
            "ConfidenceIntervalHigh":8.10,
            "StandardError":0.39
         },
         "New York":{
            "Value":8.10,
            "ConfidenceIntervalLow":7.30,
            "ConfidenceIntervalHigh":8.90,
            "StandardError":0.41
         },
         "North Carolina":{
            "Value":8.50,
            "ConfidenceIntervalLow":8.00,
            "ConfidenceIntervalHigh":9.00,
            "StandardError":0.25
         },
         "North Dakota":{
            "Value":6.70,
            "ConfidenceIntervalLow":5.90,
            "ConfidenceIntervalHigh":7.60,
            "StandardError":0.44
         },
         "Ohio":{
            "Value":7.70,
            "ConfidenceIntervalLow":6.90,
            "ConfidenceIntervalHigh":8.60,
            "StandardError":0.42
         },
         "Oklahoma":{
            "Value":8.90,
            "ConfidenceIntervalLow":8.20,
            "ConfidenceIntervalHigh":9.70,
            "StandardError":0.37
         },
         "Oregon":{
            "Value":6.70,
            "ConfidenceIntervalLow":6.20,
            "ConfidenceIntervalHigh":7.20,
            "StandardError":0.24
         },
         "Pennsylvania":{
            "Value":8.10,
            "ConfidenceIntervalLow":7.50,
            "ConfidenceIntervalHigh":8.80,
            "StandardError":0.33
         },
         "Rhode Island":{
            "Value":6.40,
            "ConfidenceIntervalLow":5.60,
            "ConfidenceIntervalHigh":7.30,
            "StandardError":0.42
         },
         "South Carolina":{
            "Value":10.30,
            "ConfidenceIntervalLow":9.60,
            "ConfidenceIntervalHigh":11.10,
            "StandardError":0.37
         },
         "South Dakota":{
            "Value":6.40,
            "ConfidenceIntervalLow":5.80,
            "ConfidenceIntervalHigh":7.10,
            "StandardError":0.31
         },
         "Tennessee":{
            "Value":9.10,
            "ConfidenceIntervalLow":8.10,
            "ConfidenceIntervalHigh":10.10,
            "StandardError":0.51
         },
         "Texas":{
            "Value":7.90,
            "ConfidenceIntervalLow":7.20,
            "ConfidenceIntervalHigh":8.70,
            "StandardError":0.36
         },
         "Utah":{
            "Value":5.50,
            "ConfidenceIntervalLow":4.90,
            "ConfidenceIntervalHigh":6.30,
            "StandardError":0.35
         },
         "Vermont":{
            "Value":6.00,
            "ConfidenceIntervalLow":5.40,
            "ConfidenceIntervalHigh":6.70,
            "StandardError":0.32
         },
         "Virginia":{
            "Value":6.90,
            "ConfidenceIntervalLow":6.20,
            "ConfidenceIntervalHigh":7.70,
            "StandardError":0.38
         },
         "Washington":{
            "Value":6.30,
            "ConfidenceIntervalLow":6.00,
            "ConfidenceIntervalHigh":6.70,
            "StandardError":0.19
         },
         "West Virginia":{
            "Value":10.40,
            "ConfidenceIntervalLow":9.40,
            "ConfidenceIntervalHigh":11.60,
            "StandardError":0.55
         },
         "Wisconsin":{
            "Value":6.60,
            "ConfidenceIntervalLow":5.80,
            "ConfidenceIntervalHigh":7.40,
            "StandardError":0.39
         },
         "Wyoming":{
            "Value":6.50,
            "ConfidenceIntervalLow":5.80,
            "ConfidenceIntervalHigh":7.30,
            "StandardError":0.37
         }
      },
    "2007":
      {
         "Alabama":{
            "Value":10.30,
            "ConfidenceIntervalLow":9.50,
            "ConfidenceIntervalHigh":11.20,
            "StandardError":0.44
         },
         "Alaska":{
            "Value":6.10,
            "ConfidenceIntervalLow":4.80,
            "ConfidenceIntervalHigh":7.70,
            "StandardError":0.71
         },
         "Arizona":{
            "Value":8.40,
            "ConfidenceIntervalLow":7.20,
            "ConfidenceIntervalHigh":9.90,
            "StandardError":0.68
         },
         "Arkansas":{
            "Value":9.20,
            "ConfidenceIntervalLow":8.40,
            "ConfidenceIntervalHigh":10.10,
            "StandardError":0.43
         },
         "California":{
            "Value":7.60,
            "ConfidenceIntervalLow":6.90,
            "ConfidenceIntervalHigh":8.40,
            "StandardError":0.40
         },
         "Colorado":{
            "Value":5.30,
            "ConfidenceIntervalLow":4.90,
            "ConfidenceIntervalHigh":5.80,
            "StandardError":0.22
         },
         "Connecticut":{
            "Value":7.30,
            "ConfidenceIntervalLow":6.60,
            "ConfidenceIntervalHigh":8.10,
            "StandardError":0.37
         },
         "Delaware":{
            "Value":8.70,
            "ConfidenceIntervalLow":7.70,
            "ConfidenceIntervalHigh":9.80,
            "StandardError":0.53
         },
         "District of Columbia":{
            "Value":8.10,
            "ConfidenceIntervalLow":7.20,
            "ConfidenceIntervalHigh":9.10,
            "StandardError":0.50
         },
         "Florida":{
            "Value":8.70,
            "ConfidenceIntervalLow":8.20,
            "ConfidenceIntervalHigh":9.30,
            "StandardError":0.28
         },
         "Georgia":{
            "Value":10.10,
            "ConfidenceIntervalLow":9.30,
            "ConfidenceIntervalHigh":11.00,
            "StandardError":0.43
         },
         "Hawaii":{
            "Value":7.70,
            "ConfidenceIntervalLow":6.90,
            "ConfidenceIntervalHigh":8.50,
            "StandardError":0.42
         },
         "Idaho":{
            "Value":7.90,
            "ConfidenceIntervalLow":7.10,
            "ConfidenceIntervalHigh":8.70,
            "StandardError":0.41
         },
         "Illinois":{
            "Value":8.80,
            "ConfidenceIntervalLow":7.90,
            "ConfidenceIntervalHigh":9.70,
            "StandardError":0.46
         },
         "Indiana":{
            "Value":8.50,
            "ConfidenceIntervalLow":7.70,
            "ConfidenceIntervalHigh":9.30,
            "StandardError":0.41
         },
         "Iowa":{
            "Value":6.80,
            "ConfidenceIntervalLow":6.10,
            "ConfidenceIntervalHigh":7.50,
            "StandardError":0.34
         },
         "Kansas":{
            "Value":7.30,
            "ConfidenceIntervalLow":6.70,
            "ConfidenceIntervalHigh":7.90,
            "StandardError":0.30
         },
         "Kentucky":{
            "Value":9.90,
            "ConfidenceIntervalLow":9.00,
            "ConfidenceIntervalHigh":10.80,
            "StandardError":0.46
         },
         "Louisiana":{
            "Value":10.20,
            "ConfidenceIntervalLow":9.30,
            "ConfidenceIntervalHigh":11.00,
            "StandardError":0.43
         },
         "Maine":{
            "Value":7.80,
            "ConfidenceIntervalLow":7.10,
            "ConfidenceIntervalHigh":8.60,
            "StandardError":0.37
         },
         "Maryland":{
            "Value":8.40,
            "ConfidenceIntervalLow":7.70,
            "ConfidenceIntervalHigh":9.20,
            "StandardError":0.37
         },
         "Massachusetts":{
            "Value":7.40,
            "ConfidenceIntervalLow":7.00,
            "ConfidenceIntervalHigh":7.90,
            "StandardError":0.23
         },
         "Michigan":{
            "Value":8.80,
            "ConfidenceIntervalLow":8.10,
            "ConfidenceIntervalHigh":9.50,
            "StandardError":0.36
         },
         "Minnesota":{
            "Value":5.70,
            "ConfidenceIntervalLow":5.00,
            "ConfidenceIntervalHigh":6.40,
            "StandardError":0.36
         },
         "Mississippi":{
            "Value":11.10,
            "ConfidenceIntervalLow":10.30,
            "ConfidenceIntervalHigh":11.90,
            "StandardError":0.41
         },
         "Missouri":{
            "Value":8.00,
            "ConfidenceIntervalLow":7.10,
            "ConfidenceIntervalHigh":9.00,
            "StandardError":0.48
         },
         "Montana":{
            "Value":6.60,
            "ConfidenceIntervalLow":6.00,
            "ConfidenceIntervalHigh":7.40,
            "StandardError":0.35
         },
         "Nebraska":{
            "Value":7.10,
            "ConfidenceIntervalLow":6.30,
            "ConfidenceIntervalHigh":7.90,
            "StandardError":0.41
         },
         "Nevada":{
            "Value":8.00,
            "ConfidenceIntervalLow":7.00,
            "ConfidenceIntervalHigh":9.30,
            "StandardError":0.58
         },
         "New Hampshire":{
            "Value":7.20,
            "ConfidenceIntervalLow":6.50,
            "ConfidenceIntervalHigh":7.90,
            "StandardError":0.35
         },
         "New Jersey":{
            "Value":9.20,
            "ConfidenceIntervalLow":8.40,
            "ConfidenceIntervalHigh":10.10,
            "StandardError":0.44
         },
         "New Mexico":{
            "Value":7.80,
            "ConfidenceIntervalLow":7.00,
            "ConfidenceIntervalHigh":8.70,
            "StandardError":0.42
         },
         "New York":{
            "Value":8.20,
            "ConfidenceIntervalLow":7.40,
            "ConfidenceIntervalHigh":9.00,
            "StandardError":0.39
         },
         "North Carolina":{
            "Value":9.10,
            "ConfidenceIntervalLow":8.50,
            "ConfidenceIntervalHigh":9.60,
            "StandardError":0.28
         },
         "North Dakota":{
            "Value":6.30,
            "ConfidenceIntervalLow":5.60,
            "ConfidenceIntervalHigh":7.00,
            "StandardError":0.36
         },
         "Ohio":{
            "Value":9.50,
            "ConfidenceIntervalLow":8.90,
            "ConfidenceIntervalHigh":10.10,
            "StandardError":0.32
         },
         "Oklahoma":{
            "Value":10.20,
            "ConfidenceIntervalLow":9.40,
            "ConfidenceIntervalHigh":11.00,
            "StandardError":0.41
         },
         "Oregon":{
            "Value":6.90,
            "ConfidenceIntervalLow":6.20,
            "ConfidenceIntervalHigh":7.70,
            "StandardError":0.37
         },
         "Pennsylvania":{
            "Value":8.70,
            "ConfidenceIntervalLow":7.90,
            "ConfidenceIntervalHigh":9.50,
            "StandardError":0.42
         },
         "Rhode Island":{
            "Value":7.20,
            "ConfidenceIntervalLow":6.40,
            "ConfidenceIntervalHigh":8.00,
            "StandardError":0.42
         },
         "South Carolina":{
            "Value":9.60,
            "ConfidenceIntervalLow":8.90,
            "ConfidenceIntervalHigh":10.30,
            "StandardError":0.35
         },
         "South Dakota":{
            "Value":6.70,
            "ConfidenceIntervalLow":6.10,
            "ConfidenceIntervalHigh":7.40,
            "StandardError":0.34
         },
         "Tennessee":{
            "Value":11.90,
            "ConfidenceIntervalLow":10.60,
            "ConfidenceIntervalHigh":13.40,
            "StandardError":0.71
         },
         "Texas":{
            "Value":10.30,
            "ConfidenceIntervalLow":9.70,
            "ConfidenceIntervalHigh":11.00,
            "StandardError":0.31
         },
         "Utah":{
            "Value":5.80,
            "ConfidenceIntervalLow":5.10,
            "ConfidenceIntervalHigh":6.60,
            "StandardError":0.39
         },
         "Vermont":{
            "Value":7.00,
            "ConfidenceIntervalLow":6.20,
            "ConfidenceIntervalHigh":7.80,
            "StandardError":0.39
         },
         "Virginia":{
            "Value":8.00,
            "ConfidenceIntervalLow":7.20,
            "ConfidenceIntervalHigh":8.80,
            "StandardError":0.41
         },
         "Washington":{
            "Value":7.10,
            "ConfidenceIntervalLow":6.70,
            "ConfidenceIntervalHigh":7.50,
            "StandardError":0.19
         },
         "West Virginia":{
            "Value":10.80,
            "ConfidenceIntervalLow":9.90,
            "ConfidenceIntervalHigh":11.80,
            "StandardError":0.49
         },
         "Wisconsin":{
            "Value":6.50,
            "ConfidenceIntervalLow":5.80,
            "ConfidenceIntervalHigh":7.20,
            "StandardError":0.35
         },
         "Wyoming":{
            "Value":7.00,
            "ConfidenceIntervalLow":6.30,
            "ConfidenceIntervalHigh":7.70,
            "StandardError":0.34
         }
      },
    "2008":
      {
         "Alabama":{
            "Value":11.20,
            "ConfidenceIntervalLow":10.30,
            "ConfidenceIntervalHigh":12.20,
            "StandardError":0.49
         },
         "Alaska":{
            "Value":6.70,
            "ConfidenceIntervalLow":5.30,
            "ConfidenceIntervalHigh":8.40,
            "StandardError":0.79
         },
         "Arizona":{
            "Value":7.80,
            "ConfidenceIntervalLow":6.70,
            "ConfidenceIntervalHigh":9.00,
            "StandardError":0.58
         },
         "Arkansas":{
            "Value":9.50,
            "ConfidenceIntervalLow":8.70,
            "ConfidenceIntervalHigh":10.40,
            "StandardError":0.45
         },
         "California":{
            "Value":8.50,
            "ConfidenceIntervalLow":7.90,
            "ConfidenceIntervalHigh":9.20,
            "StandardError":0.33
         },
         "Colorado":{
            "Value":6.00,
            "ConfidenceIntervalLow":5.50,
            "ConfidenceIntervalHigh":6.50,
            "StandardError":0.27
         },
         "Connecticut":{
            "Value":6.80,
            "ConfidenceIntervalLow":6.10,
            "ConfidenceIntervalHigh":7.60,
            "StandardError":0.37
         },
         "Delaware":{
            "Value":8.30,
            "ConfidenceIntervalLow":7.30,
            "ConfidenceIntervalHigh":9.40,
            "StandardError":0.54
         },
         "District of Columbia":{
            "Value":8.00,
            "ConfidenceIntervalLow":7.10,
            "ConfidenceIntervalHigh":8.90,
            "StandardError":0.47
         },
         "Florida":{
            "Value":9.50,
            "ConfidenceIntervalLow":8.70,
            "ConfidenceIntervalHigh":10.50,
            "StandardError":0.45
         },
         "Georgia":{
            "Value":9.90,
            "ConfidenceIntervalLow":8.90,
            "ConfidenceIntervalHigh":10.90,
            "StandardError":0.52
         },
         "Hawaii":{
            "Value":8.20,
            "ConfidenceIntervalLow":7.40,
            "ConfidenceIntervalHigh":9.10,
            "StandardError":0.44
         },
         "Idaho":{
            "Value":7.00,
            "ConfidenceIntervalLow":6.30,
            "ConfidenceIntervalHigh":7.80,
            "StandardError":0.38
         },
         "Illinois":{
            "Value":8.30,
            "ConfidenceIntervalLow":7.50,
            "ConfidenceIntervalHigh":9.30,
            "StandardError":0.44
         },
         "Indiana":{
            "Value":9.60,
            "ConfidenceIntervalLow":8.50,
            "ConfidenceIntervalHigh":10.70,
            "StandardError":0.56
         },
         "Iowa":{
            "Value":7.00,
            "ConfidenceIntervalLow":6.40,
            "ConfidenceIntervalHigh":7.70,
            "StandardError":0.34
         },
         "Kansas":{
            "Value":8.10,
            "ConfidenceIntervalLow":7.50,
            "ConfidenceIntervalHigh":8.80,
            "StandardError":0.32
         },
         "Kentucky":{
            "Value":9.90,
            "ConfidenceIntervalLow":9.10,
            "ConfidenceIntervalHigh":10.70,
            "StandardError":0.42
         },
         "Louisiana":{
            "Value":10.70,
            "ConfidenceIntervalLow":9.80,
            "ConfidenceIntervalHigh":11.60,
            "StandardError":0.44
         },
         "Maine":{
            "Value":8.30,
            "ConfidenceIntervalLow":7.60,
            "ConfidenceIntervalHigh":9.00,
            "StandardError":0.38
         },
         "Maryland":{
            "Value":8.70,
            "ConfidenceIntervalLow":8.00,
            "ConfidenceIntervalHigh":9.40,
            "StandardError":0.37
         },
         "Massachusetts":{
            "Value":7.20,
            "ConfidenceIntervalLow":6.70,
            "ConfidenceIntervalHigh":7.70,
            "StandardError":0.24
         },
         "Michigan":{
            "Value":9.10,
            "ConfidenceIntervalLow":8.40,
            "ConfidenceIntervalHigh":9.80,
            "StandardError":0.34
         },
         "Minnesota":{
            "Value":5.90,
            "ConfidenceIntervalLow":5.20,
            "ConfidenceIntervalHigh":6.70,
            "StandardError":0.36
         },
         "Mississippi":{
            "Value":11.30,
            "ConfidenceIntervalLow":10.50,
            "ConfidenceIntervalHigh":12.20,
            "StandardError":0.44
         },
         "Missouri":{
            "Value":9.10,
            "ConfidenceIntervalLow":8.20,
            "ConfidenceIntervalHigh":10.20,
            "StandardError":0.53
         },
         "Montana":{
            "Value":6.50,
            "ConfidenceIntervalLow":5.90,
            "ConfidenceIntervalHigh":7.20,
            "StandardError":0.33
         },
         "Nebraska":{
            "Value":7.80,
            "ConfidenceIntervalLow":7.10,
            "ConfidenceIntervalHigh":8.50,
            "StandardError":0.36
         },
         "Nevada":{
            "Value":8.60,
            "ConfidenceIntervalLow":7.50,
            "ConfidenceIntervalHigh":9.80,
            "StandardError":0.60
         },
         "New Hampshire":{
            "Value":7.20,
            "ConfidenceIntervalLow":6.60,
            "ConfidenceIntervalHigh":8.00,
            "StandardError":0.36
         },
         "New Jersey":{
            "Value":8.40,
            "ConfidenceIntervalLow":7.80,
            "ConfidenceIntervalHigh":9.00,
            "StandardError":0.31
         },
         "New Mexico":{
            "Value":7.90,
            "ConfidenceIntervalLow":7.10,
            "ConfidenceIntervalHigh":8.70,
            "StandardError":0.41
         },
         "New York":{
            "Value":8.40,
            "ConfidenceIntervalLow":7.70,
            "ConfidenceIntervalHigh":9.20,
            "StandardError":0.38
         },
         "North Carolina":{
            "Value":9.30,
            "ConfidenceIntervalLow":8.80,
            "ConfidenceIntervalHigh":9.90,
            "StandardError":0.29
         },
         "North Dakota":{
            "Value":7.60,
            "ConfidenceIntervalLow":6.80,
            "ConfidenceIntervalHigh":8.40,
            "StandardError":0.41
         },
         "Ohio":{
            "Value":9.90,
            "ConfidenceIntervalLow":9.30,
            "ConfidenceIntervalHigh":10.60,
            "StandardError":0.34
         },
         "Oklahoma":{
            "Value":10.10,
            "ConfidenceIntervalLow":9.40,
            "ConfidenceIntervalHigh":10.90,
            "StandardError":0.38
         },
         "Oregon":{
            "Value":6.90,
            "ConfidenceIntervalLow":6.20,
            "ConfidenceIntervalHigh":7.70,
            "StandardError":0.39
         },
         "Pennsylvania":{
            "Value":8.80,
            "ConfidenceIntervalLow":8.20,
            "ConfidenceIntervalHigh":9.50,
            "StandardError":0.35
         },
         "Rhode Island":{
            "Value":7.40,
            "ConfidenceIntervalLow":6.70,
            "ConfidenceIntervalHigh":8.30,
            "StandardError":0.42
         },
         "South Carolina":{
            "Value":10.10,
            "ConfidenceIntervalLow":9.30,
            "ConfidenceIntervalHigh":11.00,
            "StandardError":0.43
         },
         "South Dakota":{
            "Value":6.60,
            "ConfidenceIntervalLow":6.00,
            "ConfidenceIntervalHigh":7.30,
            "StandardError":0.32
         },
         "Tennessee":{
            "Value":10.40,
            "ConfidenceIntervalLow":9.40,
            "ConfidenceIntervalHigh":11.50,
            "StandardError":0.54
         },
         "Texas":{
            "Value":9.70,
            "ConfidenceIntervalLow":8.90,
            "ConfidenceIntervalHigh":10.50,
            "StandardError":0.41
         },
         "Utah":{
            "Value":6.10,
            "ConfidenceIntervalLow":5.40,
            "ConfidenceIntervalHigh":6.80,
            "StandardError":0.36
         },
         "Vermont":{
            "Value":6.40,
            "ConfidenceIntervalLow":5.80,
            "ConfidenceIntervalHigh":7.00,
            "StandardError":0.30
         },
         "Virginia":{
            "Value":7.90,
            "ConfidenceIntervalLow":7.10,
            "ConfidenceIntervalHigh":8.80,
            "StandardError":0.42
         },
         "Washington":{
            "Value":6.90,
            "ConfidenceIntervalLow":6.50,
            "ConfidenceIntervalHigh":7.30,
            "StandardError":0.20
         },
         "West Virginia":{
            "Value":11.90,
            "ConfidenceIntervalLow":10.90,
            "ConfidenceIntervalHigh":13.10,
            "StandardError":0.55
         },
         "Wisconsin":{
            "Value":7.20,
            "ConfidenceIntervalLow":6.40,
            "ConfidenceIntervalHigh":8.10,
            "StandardError":0.44
         },
         "Wyoming":{
            "Value":7.40,
            "ConfidenceIntervalLow":6.70,
            "ConfidenceIntervalHigh":8.10,
            "StandardError":0.36
         }
      },
    "2009":
      {
         "Alabama":{
            "Value":12.30,
            "ConfidenceIntervalLow":11.20,
            "ConfidenceIntervalHigh":13.30,
            "StandardError":0.54
         },
         "Alaska":{
            "Value":5.80,
            "ConfidenceIntervalLow":4.70,
            "ConfidenceIntervalHigh":7.20,
            "StandardError":0.63
         },
         "Arizona":{
            "Value":8.40,
            "ConfidenceIntervalLow":7.30,
            "ConfidenceIntervalHigh":9.70,
            "StandardError":0.59
         },
         "Arkansas":{
            "Value":10.10,
            "ConfidenceIntervalLow":9.10,
            "ConfidenceIntervalHigh":11.30,
            "StandardError":0.57
         },
         "California":{
            "Value":9.10,
            "ConfidenceIntervalLow":8.60,
            "ConfidenceIntervalHigh":9.70,
            "StandardError":0.29
         },
         "Colorado":{
            "Value":5.80,
            "ConfidenceIntervalLow":5.30,
            "ConfidenceIntervalHigh":6.30,
            "StandardError":0.26
         },
         "Connecticut":{
            "Value":6.70,
            "ConfidenceIntervalLow":6.00,
            "ConfidenceIntervalHigh":7.40,
            "StandardError":0.35
         },
         "Delaware":{
            "Value":8.10,
            "ConfidenceIntervalLow":7.20,
            "ConfidenceIntervalHigh":9.20,
            "StandardError":0.51
         },
         "District of Columbia":{
            "Value":7.50,
            "ConfidenceIntervalLow":6.60,
            "ConfidenceIntervalHigh":8.50,
            "StandardError":0.49
         },
         "Florida":{
            "Value":9.80,
            "ConfidenceIntervalLow":9.00,
            "ConfidenceIntervalHigh":10.70,
            "StandardError":0.45
         },
         "Georgia":{
            "Value":9.50,
            "ConfidenceIntervalLow":8.60,
            "ConfidenceIntervalHigh":10.60,
            "StandardError":0.53
         },
         "Hawaii":{
            "Value":8.50,
            "ConfidenceIntervalLow":7.60,
            "ConfidenceIntervalHigh":9.40,
            "StandardError":0.44
         },
         "Idaho":{
            "Value":8.00,
            "ConfidenceIntervalLow":7.20,
            "ConfidenceIntervalHigh":8.80,
            "StandardError":0.41
         },
         "Illinois":{
            "Value":8.20,
            "ConfidenceIntervalLow":7.40,
            "ConfidenceIntervalHigh":9.00,
            "StandardError":0.42
         },
         "Indiana":{
            "Value":9.30,
            "ConfidenceIntervalLow":8.70,
            "ConfidenceIntervalHigh":10.00,
            "StandardError":0.35
         },
         "Iowa":{
            "Value":7.60,
            "ConfidenceIntervalLow":6.90,
            "ConfidenceIntervalHigh":8.40,
            "StandardError":0.36
         },
         "Kansas":{
            "Value":8.50,
            "ConfidenceIntervalLow":8.10,
            "ConfidenceIntervalHigh":9.00,
            "StandardError":0.23
         },
         "Kentucky":{
            "Value":11.50,
            "ConfidenceIntervalLow":10.60,
            "ConfidenceIntervalHigh":12.50,
            "StandardError":0.50
         },
         "Louisiana":{
            "Value":11.10,
            "ConfidenceIntervalLow":10.30,
            "ConfidenceIntervalHigh":11.90,
            "StandardError":0.41
         },
         "Maine":{
            "Value":8.30,
            "ConfidenceIntervalLow":7.70,
            "ConfidenceIntervalHigh":9.00,
            "StandardError":0.33
         },
         "Maryland":{
            "Value":9.30,
            "ConfidenceIntervalLow":8.50,
            "ConfidenceIntervalHigh":10.20,
            "StandardError":0.42
         },
         "Massachusetts":{
            "Value":7.90,
            "ConfidenceIntervalLow":7.30,
            "ConfidenceIntervalHigh":8.50,
            "StandardError":0.30
         },
         "Michigan":{
            "Value":9.30,
            "ConfidenceIntervalLow":8.70,
            "ConfidenceIntervalHigh":10.00,
            "StandardError":0.34
         },
         "Minnesota":{
            "Value":6.40,
            "ConfidenceIntervalLow":5.70,
            "ConfidenceIntervalHigh":7.10,
            "StandardError":0.36
         },
         "Mississippi":{
            "Value":11.60,
            "ConfidenceIntervalLow":10.90,
            "ConfidenceIntervalHigh":12.30,
            "StandardError":0.36
         },
         "Missouri":{
            "Value":7.90,
            "ConfidenceIntervalLow":7.10,
            "ConfidenceIntervalHigh":8.90,
            "StandardError":0.45
         },
         "Montana":{
            "Value":6.80,
            "ConfidenceIntervalLow":6.20,
            "ConfidenceIntervalHigh":7.40,
            "StandardError":0.32
         },
         "Nebraska":{
            "Value":7.50,
            "ConfidenceIntervalLow":6.90,
            "ConfidenceIntervalHigh":8.10,
            "StandardError":0.30
         },
         "Nevada":{
            "Value":7.90,
            "ConfidenceIntervalLow":6.80,
            "ConfidenceIntervalHigh":9.20,
            "StandardError":0.63
         },
         "New Hampshire":{
            "Value":7.10,
            "ConfidenceIntervalLow":6.40,
            "ConfidenceIntervalHigh":7.90,
            "StandardError":0.39
         },
         "New Jersey":{
            "Value":8.70,
            "ConfidenceIntervalLow":8.00,
            "ConfidenceIntervalHigh":9.50,
            "StandardError":0.37
         },
         "New Mexico":{
            "Value":8.60,
            "ConfidenceIntervalLow":7.90,
            "ConfidenceIntervalHigh":9.40,
            "StandardError":0.38
         },
         "New York":{
            "Value":8.90,
            "ConfidenceIntervalLow":8.10,
            "ConfidenceIntervalHigh":9.70,
            "StandardError":0.42
         },
         "North Carolina":{
            "Value":9.60,
            "ConfidenceIntervalLow":8.90,
            "ConfidenceIntervalHigh":10.40,
            "StandardError":0.40
         },
         "North Dakota":{
            "Value":7.50,
            "ConfidenceIntervalLow":6.80,
            "ConfidenceIntervalHigh":8.30,
            "StandardError":0.40
         },
         "Ohio":{
            "Value":10.10,
            "ConfidenceIntervalLow":9.40,
            "ConfidenceIntervalHigh":10.90,
            "StandardError":0.38
         },
         "Oklahoma":{
            "Value":11.00,
            "ConfidenceIntervalLow":10.20,
            "ConfidenceIntervalHigh":11.80,
            "StandardError":0.41
         },
         "Oregon":{
            "Value":8.30,
            "ConfidenceIntervalLow":7.30,
            "ConfidenceIntervalHigh":9.30,
            "StandardError":0.53
         },
         "Pennsylvania":{
            "Value":9.10,
            "ConfidenceIntervalLow":8.40,
            "ConfidenceIntervalHigh":9.80,
            "StandardError":0.37
         },
         "Rhode Island":{
            "Value":7.00,
            "ConfidenceIntervalLow":6.40,
            "ConfidenceIntervalHigh":7.70,
            "StandardError":0.34
         },
         "South Carolina":{
            "Value":10.40,
            "ConfidenceIntervalLow":9.50,
            "ConfidenceIntervalHigh":11.30,
            "StandardError":0.45
         },
         "South Dakota":{
            "Value":7.30,
            "ConfidenceIntervalLow":6.60,
            "ConfidenceIntervalHigh":8.00,
            "StandardError":0.35
         },
         "Tennessee":{
            "Value":10.30,
            "ConfidenceIntervalLow":9.30,
            "ConfidenceIntervalHigh":11.40,
            "StandardError":0.54
         },
         "Texas":{
            "Value":9.30,
            "ConfidenceIntervalLow":8.50,
            "ConfidenceIntervalHigh":10.20,
            "StandardError":0.43
         },
         "Utah":{
            "Value":6.10,
            "ConfidenceIntervalLow":5.60,
            "ConfidenceIntervalHigh":6.60,
            "StandardError":0.26
         },
         "Vermont":{
            "Value":6.20,
            "ConfidenceIntervalLow":5.60,
            "ConfidenceIntervalHigh":6.80,
            "StandardError":0.30
         },
         "Virginia":{
            "Value":8.20,
            "ConfidenceIntervalLow":7.40,
            "ConfidenceIntervalHigh":9.10,
            "StandardError":0.45
         },
         "Washington":{
            "Value":7.70,
            "ConfidenceIntervalLow":7.30,
            "ConfidenceIntervalHigh":8.20,
            "StandardError":0.22
         },
         "West Virginia":{
            "Value":12.40,
            "ConfidenceIntervalLow":11.40,
            "ConfidenceIntervalHigh":13.40,
            "StandardError":0.52
         },
         "Wisconsin":{
            "Value":8.20,
            "ConfidenceIntervalLow":7.30,
            "ConfidenceIntervalHigh":9.30,
            "StandardError":0.52
         },
         "Wyoming":{
            "Value":7.00,
            "ConfidenceIntervalLow":6.30,
            "ConfidenceIntervalHigh":7.70,
            "StandardError":0.35
         }
      }
}